labelize/__init__.py
labelize/run.py
labelize/capacitors/__init__.py
labelize/capacitors/capacitors.py
labelize/img/help_outline_16dp_1F1F1F.png
labelize/img/labelize.png
labelize/manual/__init__.py
labelize/manual/manual.py
labelize/resistors/__init__.py
labelize/resistors/resistors.py
labelize/util/__init__.py
labelize/util/util.py
Labelize-1.5.dist-info/LICENSE
Labelize-1.5.dist-info/METADATA
Labelize-1.5.dist-info/WHEEL
Labelize-1.5.dist-info/entry_points.txt
Labelize-1.5.dist-info/top_level.txt
Labelize-1.5.dist-info/RECORD
