Metadata-Version: 2.1
Name: Labelize
Version: 1.5
Summary: Gui utility to generate oragnizer labels
Home-page: https://github.com/nathanjshaffer/labelize
Author: Nathan Shaffer
Author-email: nathanjshaffer@gmail.com
Classifier: Programming Language :: Python :: 3
Classifier: Operating System :: OS Independent
Classifier: License :: OSI Approved :: MIT License
License-File: LICENSE
Requires-Dist: Pint
Requires-Dist: FreeSimpleGUI
Requires-Dist: configparser
Requires-Dist: Pillow
Requires-Dist: types-Pillow
